{
 "align_labels_right": 0, 
 "creation": "2019-11-15 09:06:26.162860", 
 "css": ".gutschein h1 {\n\tcolor: #94B600 !important;\n\tfont-size: 65px !important;\n}\n.gutschein h3 {\n\tmargin-top: 0px !important;\n\tfont-weight: normal !important;\n\tfont-size: 30px !important;\n}\n.gutschein h2 {\n\tcolor: #94B600 !important;\n\tfont-size: 30px !important;\n}\n.gutschein {\n\tmin-height: 500px;\n\twidth: 100%;\n}\n.print-format {\n margin-bottom: 0mm;\n}\n", 
 "custom_format": 1, 
 "disabled": 0, 
 "doc_type": "Gutschein Meier", 
 "docstatus": 0, 
 "doctype": "Print Format", 
 "font": "Default", 
 "html": "<img src=\"/assets/pflanzenfreund/images/800x400_Geschenkabo_lay.jpg\" alt=\"Jahres-Abo\" style=\"width:100%\">\n<div class=\"gutschein\" style=\"text-align: center;\">\n\t<h1>GUTSCHEIN</h1>\n\t<h3>im Wert von CHF {{ doc.betrag }}.-</h3>\n\t<p>Einl\u00f6sbar auf dem gesamten Sortiment, im Gesch\u00e4ft und Online.<br><br></p>\n\t<p>Wir freuen uns auf deinen Besuch und beraten dich gerne!<br><br></p>\n\t<p>Dein Team vom Gartencenter Meier<br><br></p>\n\t{% if doc.fuer %}\n\t<h2>Gutschein f\u00fcr {{ doc.fuer }}{% if doc.von %} von {{ doc.von }}{% endif %}</h2>\n\t{% endif %}\n\t<p>{{ doc.widmung }}</p>\n</div>\n<div style=\"text-align: center;\">\n\t<p>Garten Center Ernst Meier AG &vert; Kreuzstrasse 2 &vert; 8635 D\u00fcrnten<br>+41 55 251 71 71 &vert; gartencenter@meier-ag.ch &vert; meier-ag.ch</p>\n{{ doc.barcode }}\n<p>XXXX-XXXX-XXXX &vert; G\u00fcltig bis {{ doc.valid_till.strftime('%d.%m.%Y') }}</p>\n</div>", 
 "idx": 0, 
 "line_breaks": 0, 
 "modified": "2019-11-18 10:09:09.552583", 
 "modified_by": "Administrator", 
 "module": "Pflanzenfreund", 
 "name": "Vorschau", 
 "owner": "Administrator", 
 "print_format_builder": 1, 
 "print_format_type": "Server", 
 "show_section_headings": 0, 
 "standard": "Yes"
}